anno/__init__.py
anno/annoapp.py
anno/anno/__init__.py
anno/anno/app.py
anno/anno/config.py
anno/anno/notes.py
anno/anno/render.py
anno/anno/static/.DS_Store
anno/anno/static/anno.css
anno/anno/static/anno.js
anno/anno/static/highlight-default.css
anno/anno/static/highlight-espresso.css
anno/anno/static/highlight-haddock.css
anno/anno/static/highlight-kate.css
anno/anno/static/highlight-monochrome.css
anno/anno/static/highlight-pygments.css
anno/anno/static/highlight-tango.css
anno/anno/static/highlight.css
anno/anno/static/jquery.min.js
anno/anno/static/markdown.css
anno/anno/static/katex/.DS_Store
anno/anno/static/katex/auto-render.min.js
anno/anno/static/katex/katex.min.css
anno/anno/static/katex/katex.min.js
anno/anno/static/katex/katex.mjs
anno/anno/static/katex/fonts/KaTeX_AMS-Regular.ttf
anno/anno/static/katex/fonts/KaTeX_AMS-Regular.woff
anno/anno/static/katex/fonts/KaTeX_AMS-Regular.woff2
anno/anno/static/katex/fonts/KaTeX_Caligraphic-Bold.ttf
anno/anno/static/katex/fonts/KaTeX_Caligraphic-Bold.woff
anno/anno/static/katex/fonts/KaTeX_Caligraphic-Bold.woff2
anno/anno/static/katex/fonts/KaTeX_Caligraphic-Regular.ttf
anno/anno/static/katex/fonts/KaTeX_Caligraphic-Regular.woff
anno/anno/static/katex/fonts/KaTeX_Caligraphic-Regular.woff2
anno/anno/static/katex/fonts/KaTeX_Fraktur-Bold.ttf
anno/anno/static/katex/fonts/KaTeX_Fraktur-Bold.woff
anno/anno/static/katex/fonts/KaTeX_Fraktur-Bold.woff2
anno/anno/static/katex/fonts/KaTeX_Fraktur-Regular.ttf
anno/anno/static/katex/fonts/KaTeX_Fraktur-Regular.woff
anno/anno/static/katex/fonts/KaTeX_Fraktur-Regular.woff2
anno/anno/static/katex/fonts/KaTeX_Main-Bold.ttf
anno/anno/static/katex/fonts/KaTeX_Main-Bold.woff
anno/anno/static/katex/fonts/KaTeX_Main-Bold.woff2
anno/anno/static/katex/fonts/KaTeX_Main-BoldItalic.ttf
anno/anno/static/katex/fonts/KaTeX_Main-BoldItalic.woff
anno/anno/static/katex/fonts/KaTeX_Main-BoldItalic.woff2
anno/anno/static/katex/fonts/KaTeX_Main-Italic.ttf
anno-0.0.4.dist-info/METADATA
anno-0.0.4.dist-info/WHEEL
anno-0.0.4.dist-info/entry_points.txt
anno-0.0.4.dist-info/top_level.txt
anno-0.0.4.dist-info/RECORD
